{
"meta":{"test_sets":[],"test_metrics":[],"learn_metrics":[{"best_value":"Min","name":"RMSE"}],"launch_mode":"Train","parameters":"","iteration_count":100,"learn_sets":["learn"],"name":"experiment"},
"iterations":[
{"learn":[14.005006],"iteration":0,"passed_time":0.001234459168,"remaining_time":0.1222114577},
{"learn":[13.14441192],"iteration":1,"passed_time":0.002242288194,"remaining_time":0.1098721215},
{"learn":[12.34258257],"iteration":2,"passed_time":0.003235488793,"remaining_time":0.1046141376},
{"learn":[11.64527793],"iteration":3,"passed_time":0.00390275853,"remaining_time":0.09366620473},
{"learn":[11.02766183],"iteration":4,"passed_time":0.004630997526,"remaining_time":0.08798895299},
{"learn":[10.43485794],"iteration":5,"passed_time":0.005886846258,"remaining_time":0.09222725804},
{"learn":[9.890641275],"iteration":6,"passed_time":0.007015187035,"remaining_time":0.0932017706},
{"learn":[9.492161212],"iteration":7,"passed_time":0.008225227554,"remaining_time":0.09459011688},
{"learn":[9.105082953],"iteration":8,"passed_time":0.009448925735,"remaining_time":0.09553913799},
{"learn":[8.674157135],"iteration":9,"passed_time":0.01032172319,"remaining_time":0.09289550871},
{"learn":[8.341743544],"iteration":10,"passed_time":0.01135227853,"remaining_time":0.09185025359},
{"learn":[8.049372916],"iteration":11,"passed_time":0.01257688871,"remaining_time":0.09223051723},
{"learn":[7.757318612],"iteration":12,"passed_time":0.01389736734,"remaining_time":0.09300545838},
{"learn":[7.522206899],"iteration":13,"passed_time":0.01506990137,"remaining_time":0.09257225125},
{"learn":[7.297756655],"iteration":14,"passed_time":0.01606118722,"remaining_time":0.09101339422},
{"learn":[7.088359431],"iteration":15,"passed_time":0.01706284426,"remaining_time":0.08957993235},
{"learn":[6.882113791],"iteration":16,"passed_time":0.01804706212,"remaining_time":0.08811212681},
{"learn":[6.704728832],"iteration":17,"passed_time":0.01901385233,"remaining_time":0.08661866059},
{"learn":[6.563881962],"iteration":18,"passed_time":0.01998849755,"remaining_time":0.08521412113},
{"learn":[6.418790279],"iteration":19,"passed_time":0.02084886512,"remaining_time":0.08339546047},
{"learn":[6.315756953],"iteration":20,"passed_time":0.02162572048,"remaining_time":0.08135390085},
{"learn":[6.210157751],"iteration":21,"passed_time":0.0224203877,"remaining_time":0.0794904655},
{"learn":[6.115058449],"iteration":22,"passed_time":0.02324428426,"remaining_time":0.07781782122},
{"learn":[6.014819884],"iteration":23,"passed_time":0.02397933274,"remaining_time":0.07593455369},
{"learn":[5.93117229],"iteration":24,"passed_time":0.02477593667,"remaining_time":0.07432781},
{"learn":[5.844857622],"iteration":25,"passed_time":0.02569375531,"remaining_time":0.07312838049},
{"learn":[5.771145213],"iteration":26,"passed_time":0.02645172166,"remaining_time":0.07151761782},
{"learn":[5.704018229],"iteration":27,"passed_time":0.02708768627,"remaining_time":0.0696540504},
{"learn":[5.665806474],"iteration":28,"passed_time":0.02772372006,"remaining_time":0.06787531462},
{"learn":[5.616500369],"iteration":29,"passed_time":0.0284318657,"remaining_time":0.06634101997},
{"learn":[5.558023666],"iteration":30,"passed_time":0.02915904243,"remaining_time":0.06490238477},
{"learn":[5.510080976],"iteration":31,"passed_time":0.02982610686,"remaining_time":0.06338047708},
{"learn":[5.468747792],"iteration":32,"passed_time":0.0306675393,"remaining_time":0.06226439798},
{"learn":[5.429275534],"iteration":33,"passed_time":0.03125610305,"remaining_time":0.0606736118},
{"learn":[5.402117324],"iteration":34,"passed_time":0.03190613036,"remaining_time":0.05925424209},
{"learn":[5.367635151],"iteration":35,"passed_time":0.03261525123,"remaining_time":0.05798266886},
{"learn":[5.345181232],"iteration":36,"passed_time":0.0332458625,"remaining_time":0.05660781993},
{"learn":[5.319151269],"iteration":37,"passed_time":0.03386870913,"remaining_time":0.05525947279},
{"learn":[5.296134146],"iteration":38,"passed_time":0.03446357764,"remaining_time":0.05390457016},
{"learn":[5.269629003],"iteration":39,"passed_time":0.03500036464,"remaining_time":0.05250054696},
{"learn":[5.251147059],"iteration":40,"passed_time":0.03564591974,"remaining_time":0.05129534792},
{"learn":[5.248003302],"iteration":41,"passed_time":0.03588374678,"remaining_time":0.04955374556},
{"learn":[5.232376509],"iteration":42,"passed_time":0.0364121071,"remaining_time":0.04826721173},
{"learn":[5.213524255],"iteration":43,"passed_time":0.03704778159,"remaining_time":0.04715172202},
{"learn":[5.189691584],"iteration":44,"passed_time":0.03764782305,"remaining_time":0.04601400595},
{"learn":[5.166052198],"iteration":45,"passed_time":0.03827409228,"remaining_time":0.04493045616},
{"learn":[5.140406659],"iteration":46,"passed_time":0.03887350814,"remaining_time":0.04383608365},
{"learn":[5.118929684],"iteration":47,"passed_time":0.03942508573,"remaining_time":0.04271050954},
{"learn":[5.108792602],"iteration":48,"passed_time":0.04010328383,"remaining_time":0.04174015256},
{"learn":[5.098141225],"iteration":49,"passed_time":0.04077327915,"remaining_time":0.04077327915},
{"learn":[5.085926393],"iteration":50,"passed_time":0.0414590455,"remaining_time":0.03983320058},
{"learn":[5.067816804],"iteration":51,"passed_time":0.04220163434,"remaining_time":0.03895535477},
{"learn":[5.049834901],"iteration":52,"passed_time":0.04292350273,"remaining_time":0.03806423827},
{"learn":[5.03838627],"iteration":53,"passed_time":0.04344349215,"remaining_time":0.03700741924},
{"learn":[5.033534248],"iteration":54,"passed_time":0.04389613241,"remaining_time":0.03591501742},
{"learn":[5.023726885],"iteration":55,"passed_time":0.04466993042,"remaining_time":0.03509780247},
{"learn":[5.01290392],"iteration":56,"passed_time":0.04544749246,"remaining_time":0.03428495045},
{"learn":[5.005569127],"iteration":57,"passed_time":0.04607774257,"remaining_time":0.03336664117},
{"learn":[4.989969032],"iteration":58,"passed_time":0.04662884297,"remaining_time":0.03240309426},
{"learn":[4.976762446],"iteration":59,"passed_time":0.04726207455,"remaining_time":0.0315080497},
{"learn":[4.967222715],"iteration":60,"passed_time":0.0478806156,"remaining_time":0.03061219686},
{"learn":[4.954407599],"iteration":61,"passed_time":0.04852219986,"remaining_time":0.02973941282},
{"learn":[4.942125056],"iteration":62,"passed_time":0.04908061261,"remaining_time":0.02882512169},
{"learn":[4.930230716],"iteration":63,"passed_time":0.04962652108,"remaining_time":0.02791491811},
{"learn":[4.921695642],"iteration":64,"passed_time":0.05033477347,"remaining_time":0.02710333956},
{"learn":[4.906405625],"iteration":65,"passed_time":0.05098878427,"remaining_time":0.02626694947},
{"learn":[4.894330248],"iteration":66,"passed_time":0.0515105776,"remaining_time":0.0253708815},
{"learn":[4.88211557],"iteration":67,"passed_time":0.05211738429,"remaining_time":0.0245258279},
{"learn":[4.877946398],"iteration":68,"passed_time":0.05269047753,"remaining_time":0.02367253338},
{"learn":[4.863182126],"iteration":69,"passed_time":0.05326883485,"remaining_time":0.02282950065},
{"learn":[4.84646533],"iteration":70,"passed_time":0.05390530195,"remaining_time":0.02201765854},
{"learn":[4.838014752],"iteration":71,"passed_time":0.05462313628,"remaining_time":0.02124233078},
{"learn":[4.82981137],"iteration":72,"passed_time":0.05535319965,"remaining_time":0.02047310124},
{"learn":[4.817094767],"iteration":73,"passed_time":0.0559951525,"remaining_time":0.0196739725},
{"learn":[4.808314151],"iteration":74,"passed_time":0.05656751042,"remaining_time":0.01885583681},
{"learn":[4.796235023],"iteration":75,"passed_time":0.05713178011,"remaining_time":0.01804161477},
{"learn":[4.784434534],"iteration":76,"passed_time":0.05773221434,"remaining_time":0.0172446874},
{"learn":[4.774402487],"iteration":77,"passed_time":0.05836859515,"remaining_time":0.01646293709},
{"learn":[4.76731896],"iteration":78,"passed_time":0.05900811068,"remaining_time":0.01568570031},
{"learn":[4.75934113],"iteration":79,"passed_time":0.05956523911,"remaining_time":0.01489130978},
{"learn":[4.754106378],"iteration":80,"passed_time":0.06012109774,"remaining_time":0.01410247972},
{"learn":[4.744002932],"iteration":81,"passed_time":0.06069468083,"remaining_time":0.01332322262},
{"learn":[4.731700554],"iteration":82,"passed_time":0.06124137857,"remaining_time":0.01254341489},
{"learn":[4.723284153],"iteration":83,"passed_time":0.06185035702,"remaining_time":0.01178102038},
{"learn":[4.712232782],"iteration":84,"passed_time":0.06241216633,"remaining_time":0.0110139117},
{"learn":[4.703046867],"iteration":85,"passed_time":0.06294819643,"remaining_time":0.01024738081},
{"learn":[4.698601855],"iteration":86,"passed_time":0.06356936821,"remaining_time":0.009498871112},
{"learn":[4.692429407],"iteration":87,"passed_time":0.06415323323,"remaining_time":0.008748168168},
{"learn":[4.675027364],"iteration":88,"passed_time":0.06475824494,"remaining_time":0.008003828026},
{"learn":[4.662368584],"iteration":89,"passed_time":0.06525834855,"remaining_time":0.007250927616},
{"learn":[4.646206172],"iteration":90,"passed_time":0.0658856819,"remaining_time":0.006516166342},
{"learn":[4.641245848],"iteration":91,"passed_time":0.06645293121,"remaining_time":0.005778515757},
{"learn":[4.633900435],"iteration":92,"passed_time":0.06715230984,"remaining_time":0.005054474934},
{"learn":[4.624738236],"iteration":93,"passed_time":0.0677002387,"remaining_time":0.004321291832},
{"learn":[4.612798287],"iteration":94,"passed_time":0.06831757689,"remaining_time":0.003595661941},
{"learn":[4.605222001],"iteration":95,"passed_time":0.06885979274,"remaining_time":0.002869158031},
{"learn":[4.601725912],"iteration":96,"passed_time":0.06946375743,"remaining_time":0.002148363632},
{"learn":[4.59722371],"iteration":97,"passed_time":0.07005133144,"remaining_time":0.001429619009},
{"learn":[4.580235665],"iteration":98,"passed_time":0.07074362981,"remaining_time":0.0007145821193},
{"learn":[4.57591791],"iteration":99,"passed_time":0.07141903017,"remaining_time":0}
]}